embedpg/__init__.py
embedpg/core.py
resources/fetch_pg.py
resources/postgres-darwin-arm_64.txz
resources/postgres-linux-x86_64.txz
embedpg-0.1.0.dist-info/WHEEL
embedpg-0.1.0.dist-info/METADATA
embedpg-0.1.0.dist-info/license_files/LICENSE
embedpg-0.1.0.dist-info/RECORD
